{
  "timestamp": "2025-10-10T01:01:57.952Z",
  "summary": {
    "success": false,
    "passed": 1,
    "failed": 1,
    "total": 2,
    "duration": 10819
  },
  "flags": {
    "quick": false,
    "noEmulators": false,
    "fix": false
  },
  "results": [
    {
      "name": "Flutter pub get",
      "success": true,
      "duration": 1545,
      "exitCode": 0,
      "error": null,
      "logFile": "flutter-pub-get.log"
    },
    {
      "name": "Flutter analyze (ZERO tolerance)",
      "success": false,
      "duration": 6318,
      "exitCode": 1,
      "error": "6 issues found. (ran in 4.5s)",
      "logFile": "flutter-analyze-zero-tolerance-.log"
    }
  ]
}